configclasses/__init__.py
configclasses/configclasses.py
configclasses/dumpers.py
configclasses/exceptions.py
configclasses/helpers.py
configclasses/loaders.py
12factor_configclasses-2.0.1.dist-info/LICENSE
12factor_configclasses-2.0.1.dist-info/METADATA
12factor_configclasses-2.0.1.dist-info/WHEEL
12factor_configclasses-2.0.1.dist-info/RECORD
