Metadata-Version: 2.1
Name: 12factor-configclasses
Version: 2.0.1
Summary: Like dataclasses but for config.
Home-page: https://github.com/kingoodie/configclasses
License: MIT
Author: Pablo Cabezas
Author-email: pabcabsal@gmail.com
Requires-Python: >=3.9,<4.0
Classifier: License :: OSI Approved :: MIT License
Classifier: Programming Language :: Python :: 3
Classifier: Programming Language :: Python :: 3.9
Classifier: Programming Language :: Python :: 3.10
Classifier: Programming Language :: Python :: 3.11
Provides-Extra: dotenv
Provides-Extra: full
Provides-Extra: toml
Provides-Extra: yaml
Requires-Dist: python-dotenv[dotenv] (>=1.0,<2.0) ; extra == "dotenv" or extra == "full"
Requires-Dist: pyyaml[yaml] (>=6,<7) ; extra == "yaml" or extra == "full"
Requires-Dist: tomlkit[toml] (>=0.12,<0.13) ; extra == "toml" or extra == "full"
Project-URL: Repository, https://github.com/kingoodie/configclasses
